examples/__init__.py
tests/__init__.py
tests/config.py
tests/dirutils.py
tests/test_main.py
treecomp/__init__.py
treecomp/cli.py
treecomp/fs_utils.py
treecomp/ignore.py
treecomp/main.py
treecomp/path_matcher.py
treecomp/target.py
treecomp/unidiff.py
treecomp-1.0.0.dist-info/LICENSE.md
treecomp-1.0.0.dist-info/METADATA
treecomp-1.0.0.dist-info/WHEEL
treecomp-1.0.0.dist-info/entry_points.txt
treecomp-1.0.0.dist-info/top_level.txt
treecomp-1.0.0.dist-info/RECORD
