Metadata-Version: 2.1
Name: treecomp
Version: 1.0.0
Summary: Compare directory trees and output unified diff
Home-page: https://github.com/nickderobertis/treecomp
Author: Nick DeRobertis
Author-email: derobertis.nick@gmail.com
License: MIT
Project-URL: Code, https://github.com/nickderobertis/treecomp
Project-URL: Documentation, https://nickderobertis.github.io/treecomp
Classifier: Development Status :: 3 - Alpha
Classifier: Intended Audience :: Developers
Classifier: Programming Language :: Python :: 3.6
Classifier: Programming Language :: Python :: 3.7
License-File: LICENSE.md
Requires-Dist: typer
Requires-Dist: pathspec
